python_architecture_linter_grimp_extension/__init__.py
python_architecture_linter_grimp_extension/grimp_definition.py
python_architecture_linter_grimp_extension/grimp_navigators.py
python_architecture_linter_grimp_extension/node_normaliser.py
python_architecture_linter_grimp_extension-0.1.2.dist-info/METADATA
python_architecture_linter_grimp_extension-0.1.2.dist-info/WHEEL
python_architecture_linter_grimp_extension-0.1.2.dist-info/namespace_packages.txt
python_architecture_linter_grimp_extension-0.1.2.dist-info/top_level.txt
python_architecture_linter_grimp_extension-0.1.2.dist-info/RECORD
